<?xml version="1.0" encoding="UTF-8"?>
<!DOCTYPE mapper PUBLIC "-//mybatis.org//DTD Mapper 3.0//EN" "http://mybatis.org/dtd/mybatis-3-mapper.dtd">
<mapper namespace="com.fastretailing.dcp.sales.common.repository.TransactionInquirySalesTransactionDiscountMapper">
  <resultMap id="BaseResultMap" type="com.fastretailing.dcp.sales.common.entity.TransactionInquirySalesTransactionDiscount">
    <!--
      WARNING - @mbg.generated
      This element is automatically generated by MyBatis Generator, do not modify.
    -->
    <id column="order_sub_number" jdbcType="NUMERIC" property="orderSubNumber" />
    <id column="sales_transaction_id" jdbcType="VARCHAR" property="salesTransactionId" />
    <id column="detail_sub_number" jdbcType="NUMERIC" property="detailSubNumber" />
    <id column="promotion_type" jdbcType="VARCHAR" property="promotionType" />
    <id column="promotion_no" jdbcType="VARCHAR" property="promotionNo" />
    <id column="store_discount_type" jdbcType="VARCHAR" property="storeDiscountType" />
    <result column="item_discount_sub_number" jdbcType="NUMERIC" property="itemDiscountSubNumber" />
    <result column="quantity_code" jdbcType="VARCHAR" property="quantityCode" />
    <result column="discount_quantity" jdbcType="NUMERIC" property="discountQuantity" />
    <result column="discount_amount_tax_excluded_currency_code" jdbcType="VARCHAR" property="discountAmountTaxExcludedCurrencyCode" />
    <result column="discount_amount_tax_excluded" jdbcType="NUMERIC" property="discountAmountTaxExcluded" />
    <result column="discount_amount_tax_included_currency_code" jdbcType="VARCHAR" property="discountAmountTaxIncludedCurrencyCode" />
    <result column="discount_amount_tax_included" jdbcType="NUMERIC" property="discountAmountTaxIncluded" />
    <result column="create_user_id" jdbcType="VARCHAR" property="createUserId" />
    <result column="create_datetime" jdbcType="TIMESTAMP" property="createDatetime" />
    <result column="create_program_id" jdbcType="VARCHAR" property="createProgramId" />
    <result column="update_user_id" jdbcType="VARCHAR" property="updateUserId" />
    <result column="update_datetime" jdbcType="TIMESTAMP" property="updateDatetime" />
    <result column="update_program_id" jdbcType="VARCHAR" property="updateProgramId" />
  </resultMap>
  <sql id="Condition_Where_Clause">
    <!--
      WARNING - @mbg.generated
      This element is automatically generated by MyBatis Generator, do not modify.
    -->
    <where>
      <foreach collection="oredCriteria" item="criteria" separator="or">
        <if test="criteria.valid">
          <trim prefix="(" prefixOverrides="and" suffix=")">
            <foreach collection="criteria.criteria" item="criterion">
              <choose>
                <when test="criterion.noValue">
                  and ${criterion.condition}
                </when>
                <when test="criterion.singleValue">
                  and ${criterion.condition} #{criterion.value}
                </when>
                <when test="criterion.betweenValue">
                  and ${criterion.condition} #{criterion.value} and #{criterion.secondValue}
                </when>
                <when test="criterion.listValue">
                  and ${criterion.condition}
                  <foreach close=")" collection="criterion.value" item="listItem" open="(" separator=",">
                    #{listItem}
                  </foreach>
                </when>
              </choose>
            </foreach>
          </trim>
        </if>
      </foreach>
    </where>
  </sql>
  <sql id="Update_By_Condition_Where_Clause">
    <!--
      WARNING - @mbg.generated
      This element is automatically generated by MyBatis Generator, do not modify.
    -->
    <where>
      <foreach collection="example.oredCriteria" item="criteria" separator="or">
        <if test="criteria.valid">
          <trim prefix="(" prefixOverrides="and" suffix=")">
            <foreach collection="criteria.criteria" item="criterion">
              <choose>
                <when test="criterion.noValue">
                  and ${criterion.condition}
                </when>
                <when test="criterion.singleValue">
                  and ${criterion.condition} #{criterion.value}
                </when>
                <when test="criterion.betweenValue">
                  and ${criterion.condition} #{criterion.value} and #{criterion.secondValue}
                </when>
                <when test="criterion.listValue">
                  and ${criterion.condition}
                  <foreach close=")" collection="criterion.value" item="listItem" open="(" separator=",">
                    #{listItem}
                  </foreach>
                </when>
              </choose>
            </foreach>
          </trim>
        </if>
      </foreach>
    </where>
  </sql>
  <sql id="Base_Column_List">
    <!--
      WARNING - @mbg.generated
      This element is automatically generated by MyBatis Generator, do not modify.
    -->
    order_sub_number, sales_transaction_id, detail_sub_number, promotion_type, promotion_no, 
    store_discount_type, item_discount_sub_number, quantity_code, discount_quantity, 
    discount_amount_tax_excluded_currency_code, discount_amount_tax_excluded, discount_amount_tax_included_currency_code, 
    discount_amount_tax_included, create_user_id, create_datetime, create_program_id, 
    update_user_id, update_datetime, update_program_id
  </sql>
  <select id="selectByCondition" parameterType="com.fastretailing.dcp.sales.common.entity.TransactionInquirySalesTransactionDiscountCondition" resultMap="BaseResultMap">
    <!--
      WARNING - @mbg.generated
      This element is automatically generated by MyBatis Generator, do not modify.
    -->
    select
    <if test="distinct">
      distinct
    </if>
    <include refid="Base_Column_List" />
    from t_transaction_inquiry_sales_transaction_discount
    <if test="_parameter != null">
      <include refid="Condition_Where_Clause" />
    </if>
    <if test="orderByClause != null">
      order by ${orderByClause}
    </if>
  </select>
  <select id="selectByPrimaryKey" parameterType="com.fastretailing.dcp.sales.common.entity.TransactionInquirySalesTransactionDiscountKey" resultMap="BaseResultMap">
    <!--
      WARNING - @mbg.generated
      This element is automatically generated by MyBatis Generator, do not modify.
    -->
    select 
    <include refid="Base_Column_List" />
    from t_transaction_inquiry_sales_transaction_discount
    where order_sub_number = #{orderSubNumber,jdbcType=NUMERIC}
      and sales_transaction_id = #{salesTransactionId,jdbcType=VARCHAR}
      and detail_sub_number = #{detailSubNumber,jdbcType=NUMERIC}
      and promotion_type = #{promotionType,jdbcType=VARCHAR}
      and promotion_no = #{promotionNo,jdbcType=VARCHAR}
      and store_discount_type = #{storeDiscountType,jdbcType=VARCHAR}
  </select>
  <delete id="deleteByPrimaryKey" parameterType="com.fastretailing.dcp.sales.common.entity.TransactionInquirySalesTransactionDiscountKey">
    <!--
      WARNING - @mbg.generated
      This element is automatically generated by MyBatis Generator, do not modify.
    -->
    delete from t_transaction_inquiry_sales_transaction_discount
    where order_sub_number = #{orderSubNumber,jdbcType=NUMERIC}
      and sales_transaction_id = #{salesTransactionId,jdbcType=VARCHAR}
      and detail_sub_number = #{detailSubNumber,jdbcType=NUMERIC}
      and promotion_type = #{promotionType,jdbcType=VARCHAR}
      and promotion_no = #{promotionNo,jdbcType=VARCHAR}
      and store_discount_type = #{storeDiscountType,jdbcType=VARCHAR}
  </delete>
  <delete id="deleteByCondition" parameterType="com.fastretailing.dcp.sales.common.entity.TransactionInquirySalesTransactionDiscountCondition">
    <!--
      WARNING - @mbg.generated
      This element is automatically generated by MyBatis Generator, do not modify.
    -->
    delete from t_transaction_inquiry_sales_transaction_discount
    <if test="_parameter != null">
      <include refid="Condition_Where_Clause" />
    </if>
  </delete>
  <insert id="insert" parameterType="com.fastretailing.dcp.sales.common.entity.TransactionInquirySalesTransactionDiscount">
    <!--
      WARNING - @mbg.generated
      This element is automatically generated by MyBatis Generator, do not modify.
    -->
    insert into t_transaction_inquiry_sales_transaction_discount (order_sub_number, sales_transaction_id, 
      detail_sub_number, promotion_type, promotion_no, 
      store_discount_type, item_discount_sub_number, 
      quantity_code, discount_quantity, discount_amount_tax_excluded_currency_code, 
      discount_amount_tax_excluded, discount_amount_tax_included_currency_code, 
      discount_amount_tax_included, create_user_id, 
      create_datetime, create_program_id, update_user_id, 
      update_datetime, update_program_id)
    values (#{orderSubNumber,jdbcType=NUMERIC}, #{salesTransactionId,jdbcType=VARCHAR}, 
      #{detailSubNumber,jdbcType=NUMERIC}, #{promotionType,jdbcType=VARCHAR}, #{promotionNo,jdbcType=VARCHAR}, 
      #{storeDiscountType,jdbcType=VARCHAR}, #{itemDiscountSubNumber,jdbcType=NUMERIC}, 
      #{quantityCode,jdbcType=VARCHAR}, #{discountQuantity,jdbcType=NUMERIC}, #{discountAmountTaxExcludedCurrencyCode,jdbcType=VARCHAR}, 
      #{discountAmountTaxExcluded,jdbcType=NUMERIC}, #{discountAmountTaxIncludedCurrencyCode,jdbcType=VARCHAR}, 
      #{discountAmountTaxIncluded,jdbcType=NUMERIC}, #{createUserId,jdbcType=VARCHAR}, 
      #{createDatetime,jdbcType=TIMESTAMP}, #{createProgramId,jdbcType=VARCHAR}, #{updateUserId,jdbcType=VARCHAR}, 
      #{updateDatetime,jdbcType=TIMESTAMP}, #{updateProgramId,jdbcType=VARCHAR})
     ON CONFLICT DO NOTHING 
  </insert>
  <insert id="insertSelective" parameterType="com.fastretailing.dcp.sales.common.entity.TransactionInquirySalesTransactionDiscount">
    <!--
      WARNING - @mbg.generated
      This element is automatically generated by MyBatis Generator, do not modify.
    -->
    insert into t_transaction_inquiry_sales_transaction_discount
    <trim prefix="(" suffix=")" suffixOverrides=",">
      <if test="orderSubNumber != null">
        order_sub_number,
      </if>
      <if test="salesTransactionId != null">
        sales_transaction_id,
      </if>
      <if test="detailSubNumber != null">
        detail_sub_number,
      </if>
      <if test="promotionType != null">
        promotion_type,
      </if>
      <if test="promotionNo != null">
        promotion_no,
      </if>
      <if test="storeDiscountType != null">
        store_discount_type,
      </if>
      <if test="itemDiscountSubNumber != null">
        item_discount_sub_number,
      </if>
      <if test="quantityCode != null">
        quantity_code,
      </if>
      <if test="discountQuantity != null">
        discount_quantity,
      </if>
      <if test="discountAmountTaxExcludedCurrencyCode != null">
        discount_amount_tax_excluded_currency_code,
      </if>
      <if test="discountAmountTaxExcluded != null">
        discount_amount_tax_excluded,
      </if>
      <if test="discountAmountTaxIncludedCurrencyCode != null">
        discount_amount_tax_included_currency_code,
      </if>
      <if test="discountAmountTaxIncluded != null">
        discount_amount_tax_included,
      </if>
      <if test="createUserId != null">
        create_user_id,
      </if>
      <if test="createDatetime != null">
        create_datetime,
      </if>
      <if test="createProgramId != null">
        create_program_id,
      </if>
      <if test="updateUserId != null">
        update_user_id,
      </if>
      <if test="updateDatetime != null">
        update_datetime,
      </if>
      <if test="updateProgramId != null">
        update_program_id,
      </if>
    </trim>
    <trim prefix="values (" suffix=")" suffixOverrides=",">
      <if test="orderSubNumber != null">
        #{orderSubNumber,jdbcType=NUMERIC},
      </if>
      <if test="salesTransactionId != null">
        #{salesTransactionId,jdbcType=VARCHAR},
      </if>
      <if test="detailSubNumber != null">
        #{detailSubNumber,jdbcType=NUMERIC},
      </if>
      <if test="promotionType != null">
        #{promotionType,jdbcType=VARCHAR},
      </if>
      <if test="promotionNo != null">
        #{promotionNo,jdbcType=VARCHAR},
      </if>
      <if test="storeDiscountType != null">
        #{storeDiscountType,jdbcType=VARCHAR},
      </if>
      <if test="itemDiscountSubNumber != null">
        #{itemDiscountSubNumber,jdbcType=NUMERIC},
      </if>
      <if test="quantityCode != null">
        #{quantityCode,jdbcType=VARCHAR},
      </if>
      <if test="discountQuantity != null">
        #{discountQuantity,jdbcType=NUMERIC},
      </if>
      <if test="discountAmountTaxExcludedCurrencyCode != null">
        #{discountAmountTaxExcludedCurrencyCode,jdbcType=VARCHAR},
      </if>
      <if test="discountAmountTaxExcluded != null">
        #{discountAmountTaxExcluded,jdbcType=NUMERIC},
      </if>
      <if test="discountAmountTaxIncludedCurrencyCode != null">
        #{discountAmountTaxIncludedCurrencyCode,jdbcType=VARCHAR},
      </if>
      <if test="discountAmountTaxIncluded != null">
        #{discountAmountTaxIncluded,jdbcType=NUMERIC},
      </if>
      <if test="createUserId != null">
        #{createUserId,jdbcType=VARCHAR},
      </if>
      <if test="createDatetime != null">
        #{createDatetime,jdbcType=TIMESTAMP},
      </if>
      <if test="createProgramId != null">
        #{createProgramId,jdbcType=VARCHAR},
      </if>
      <if test="updateUserId != null">
        #{updateUserId,jdbcType=VARCHAR},
      </if>
      <if test="updateDatetime != null">
        #{updateDatetime,jdbcType=TIMESTAMP},
      </if>
      <if test="updateProgramId != null">
        #{updateProgramId,jdbcType=VARCHAR},
      </if>
    </trim>
     ON CONFLICT DO NOTHING 
  </insert>
  <select id="countByCondition" parameterType="com.fastretailing.dcp.sales.common.entity.TransactionInquirySalesTransactionDiscountCondition" resultType="java.lang.Long">
    <!--
      WARNING - @mbg.generated
      This element is automatically generated by MyBatis Generator, do not modify.
    -->
    select count(*) from t_transaction_inquiry_sales_transaction_discount
    <if test="_parameter != null">
      <include refid="Condition_Where_Clause" />
    </if>
  </select>
  <update id="updateByConditionSelective" parameterType="map">
    <!--
      WARNING - @mbg.generated
      This element is automatically generated by MyBatis Generator, do not modify.
    -->
    update t_transaction_inquiry_sales_transaction_discount
    <set>
      <if test="record.orderSubNumber != null">
        order_sub_number = #{record.orderSubNumber,jdbcType=NUMERIC},
      </if>
      <if test="record.salesTransactionId != null">
        sales_transaction_id = #{record.salesTransactionId,jdbcType=VARCHAR},
      </if>
      <if test="record.detailSubNumber != null">
        detail_sub_number = #{record.detailSubNumber,jdbcType=NUMERIC},
      </if>
      <if test="record.promotionType != null">
        promotion_type = #{record.promotionType,jdbcType=VARCHAR},
      </if>
      <if test="record.promotionNo != null">
        promotion_no = #{record.promotionNo,jdbcType=VARCHAR},
      </if>
      <if test="record.storeDiscountType != null">
        store_discount_type = #{record.storeDiscountType,jdbcType=VARCHAR},
      </if>
      <if test="record.itemDiscountSubNumber != null">
        item_discount_sub_number = #{record.itemDiscountSubNumber,jdbcType=NUMERIC},
      </if>
      <if test="record.quantityCode != null">
        quantity_code = #{record.quantityCode,jdbcType=VARCHAR},
      </if>
      <if test="record.discountQuantity != null">
        discount_quantity = #{record.discountQuantity,jdbcType=NUMERIC},
      </if>
      <if test="record.discountAmountTaxExcludedCurrencyCode != null">
        discount_amount_tax_excluded_currency_code = #{record.discountAmountTaxExcludedCurrencyCode,jdbcType=VARCHAR},
      </if>
      <if test="record.discountAmountTaxExcluded != null">
        discount_amount_tax_excluded = #{record.discountAmountTaxExcluded,jdbcType=NUMERIC},
      </if>
      <if test="record.discountAmountTaxIncludedCurrencyCode != null">
        discount_amount_tax_included_currency_code = #{record.discountAmountTaxIncludedCurrencyCode,jdbcType=VARCHAR},
      </if>
      <if test="record.discountAmountTaxIncluded != null">
        discount_amount_tax_included = #{record.discountAmountTaxIncluded,jdbcType=NUMERIC},
      </if>
      <if test="record.createUserId != null">
        create_user_id = #{record.createUserId,jdbcType=VARCHAR},
      </if>
      <if test="record.createDatetime != null">
        create_datetime = #{record.createDatetime,jdbcType=TIMESTAMP},
      </if>
      <if test="record.createProgramId != null">
        create_program_id = #{record.createProgramId,jdbcType=VARCHAR},
      </if>
      <if test="record.updateUserId != null">
        update_user_id = #{record.updateUserId,jdbcType=VARCHAR},
      </if>
      <if test="record.updateDatetime != null">
        update_datetime = #{record.updateDatetime,jdbcType=TIMESTAMP},
      </if>
      <if test="record.updateProgramId != null">
        update_program_id = #{record.updateProgramId,jdbcType=VARCHAR},
      </if>
    </set>
    <if test="_parameter != null">
      <include refid="Update_By_Condition_Where_Clause" />
    </if>
  </update>
  <update id="updateByCondition" parameterType="map">
    <!--
      WARNING - @mbg.generated
      This element is automatically generated by MyBatis Generator, do not modify.
    -->
    update t_transaction_inquiry_sales_transaction_discount
    set order_sub_number = #{record.orderSubNumber,jdbcType=NUMERIC},
      sales_transaction_id = #{record.salesTransactionId,jdbcType=VARCHAR},
      detail_sub_number = #{record.detailSubNumber,jdbcType=NUMERIC},
      promotion_type = #{record.promotionType,jdbcType=VARCHAR},
      promotion_no = #{record.promotionNo,jdbcType=VARCHAR},
      store_discount_type = #{record.storeDiscountType,jdbcType=VARCHAR},
      item_discount_sub_number = #{record.itemDiscountSubNumber,jdbcType=NUMERIC},
      quantity_code = #{record.quantityCode,jdbcType=VARCHAR},
      discount_quantity = #{record.discountQuantity,jdbcType=NUMERIC},
      discount_amount_tax_excluded_currency_code = #{record.discountAmountTaxExcludedCurrencyCode,jdbcType=VARCHAR},
      discount_amount_tax_excluded = #{record.discountAmountTaxExcluded,jdbcType=NUMERIC},
      discount_amount_tax_included_currency_code = #{record.discountAmountTaxIncludedCurrencyCode,jdbcType=VARCHAR},
      discount_amount_tax_included = #{record.discountAmountTaxIncluded,jdbcType=NUMERIC},
      create_user_id = #{record.createUserId,jdbcType=VARCHAR},
      create_datetime = #{record.createDatetime,jdbcType=TIMESTAMP},
      create_program_id = #{record.createProgramId,jdbcType=VARCHAR},
      update_user_id = #{record.updateUserId,jdbcType=VARCHAR},
      update_datetime = #{record.updateDatetime,jdbcType=TIMESTAMP},
      update_program_id = #{record.updateProgramId,jdbcType=VARCHAR}
    <if test="_parameter != null">
      <include refid="Update_By_Condition_Where_Clause" />
    </if>
  </update>
  <update id="updateByPrimaryKeySelective" parameterType="com.fastretailing.dcp.sales.common.entity.TransactionInquirySalesTransactionDiscount">
    <!--
      WARNING - @mbg.generated
      This element is automatically generated by MyBatis Generator, do not modify.
    -->
    update t_transaction_inquiry_sales_transaction_discount
    <set>
      <if test="itemDiscountSubNumber != null">
        item_discount_sub_number = #{itemDiscountSubNumber,jdbcType=NUMERIC},
      </if>
      <if test="quantityCode != null">
        quantity_code = #{quantityCode,jdbcType=VARCHAR},
      </if>
      <if test="discountQuantity != null">
        discount_quantity = #{discountQuantity,jdbcType=NUMERIC},
      </if>
      <if test="discountAmountTaxExcludedCurrencyCode != null">
        discount_amount_tax_excluded_currency_code = #{discountAmountTaxExcludedCurrencyCode,jdbcType=VARCHAR},
      </if>
      <if test="discountAmountTaxExcluded != null">
        discount_amount_tax_excluded = #{discountAmountTaxExcluded,jdbcType=NUMERIC},
      </if>
      <if test="discountAmountTaxIncludedCurrencyCode != null">
        discount_amount_tax_included_currency_code = #{discountAmountTaxIncludedCurrencyCode,jdbcType=VARCHAR},
      </if>
      <if test="discountAmountTaxIncluded != null">
        discount_amount_tax_included = #{discountAmountTaxIncluded,jdbcType=NUMERIC},
      </if>
      <if test="createUserId != null">
        create_user_id = #{createUserId,jdbcType=VARCHAR},
      </if>
      <if test="createDatetime != null">
        create_datetime = #{createDatetime,jdbcType=TIMESTAMP},
      </if>
      <if test="createProgramId != null">
        create_program_id = #{createProgramId,jdbcType=VARCHAR},
      </if>
      <if test="updateUserId != null">
        update_user_id = #{updateUserId,jdbcType=VARCHAR},
      </if>
      <if test="updateDatetime != null">
        update_datetime = #{updateDatetime,jdbcType=TIMESTAMP},
      </if>
      <if test="updateProgramId != null">
        update_program_id = #{updateProgramId,jdbcType=VARCHAR},
      </if>
    </set>
    where order_sub_number = #{orderSubNumber,jdbcType=NUMERIC}
      and sales_transaction_id = #{salesTransactionId,jdbcType=VARCHAR}
      and detail_sub_number = #{detailSubNumber,jdbcType=NUMERIC}
      and promotion_type = #{promotionType,jdbcType=VARCHAR}
      and promotion_no = #{promotionNo,jdbcType=VARCHAR}
      and store_discount_type = #{storeDiscountType,jdbcType=VARCHAR}
  </update>
  <update id="updateByPrimaryKey" parameterType="com.fastretailing.dcp.sales.common.entity.TransactionInquirySalesTransactionDiscount">
    <!--
      WARNING - @mbg.generated
      This element is automatically generated by MyBatis Generator, do not modify.
    -->
    update t_transaction_inquiry_sales_transaction_discount
    set item_discount_sub_number = #{itemDiscountSubNumber,jdbcType=NUMERIC},
      quantity_code = #{quantityCode,jdbcType=VARCHAR},
      discount_quantity = #{discountQuantity,jdbcType=NUMERIC},
      discount_amount_tax_excluded_currency_code = #{discountAmountTaxExcludedCurrencyCode,jdbcType=VARCHAR},
      discount_amount_tax_excluded = #{discountAmountTaxExcluded,jdbcType=NUMERIC},
      discount_amount_tax_included_currency_code = #{discountAmountTaxIncludedCurrencyCode,jdbcType=VARCHAR},
      discount_amount_tax_included = #{discountAmountTaxIncluded,jdbcType=NUMERIC},
      create_user_id = #{createUserId,jdbcType=VARCHAR},
      create_datetime = #{createDatetime,jdbcType=TIMESTAMP},
      create_program_id = #{createProgramId,jdbcType=VARCHAR},
      update_user_id = #{updateUserId,jdbcType=VARCHAR},
      update_datetime = #{updateDatetime,jdbcType=TIMESTAMP},
      update_program_id = #{updateProgramId,jdbcType=VARCHAR}
    where order_sub_number = #{orderSubNumber,jdbcType=NUMERIC}
      and sales_transaction_id = #{salesTransactionId,jdbcType=VARCHAR}
      and detail_sub_number = #{detailSubNumber,jdbcType=NUMERIC}
      and promotion_type = #{promotionType,jdbcType=VARCHAR}
      and promotion_no = #{promotionNo,jdbcType=VARCHAR}
      and store_discount_type = #{storeDiscountType,jdbcType=VARCHAR}
  </update>
</mapper>
